{"nodes": [{"id": "dashboardhomeclient", "label": "DashboardHomeClient.tsx", "file_type": "code", "source_file": "src\\components\\dashboard\\DashboardHomeClient.tsx", "source_location": "L1"}, {"id": "dashboardhomeclient_scrolltohash", "label": "scrollToHash()", "file_type": "code", "source_file": "src\\components\\dashboard\\DashboardHomeClient.tsx", "source_location": "L38"}], "edges": [{"source": "dashboardhomeclient", "target": "react", "relation": "imports_from", "confidence": "EXTRACTED", "source_file": "src\\components\\dashboard\\DashboardHomeClient.tsx", "source_location": "L3", "weight": 1.0}, {"source": "dashboardhomeclient", "target": "librarysearchcontext", "relation": "imports_from", "confidence": "EXTRACTED", "source_file": "src\\components\\dashboard\\DashboardHomeClient.tsx", "source_location": "L4", "weight": 1.0}, {"source": "dashboardhomeclient", "target": "dashboardblueprintdecor", "relation": "imports_from", "confidence": "EXTRACTED", "source_file": "src\\components\\dashboard\\DashboardHomeClient.tsx", "source_location": "L5", "weight": 1.0}, {"source": "dashboardhomeclient", "target": "dashboarddraftbanner", "relation": "imports_from", "confidence": "EXTRACTED", "source_file": "src\\components\\dashboard\\DashboardHomeClient.tsx", "source_location": "L6", "weight": 1.0}, {"source": "dashboardhomeclient", "target": "dashboardhero", "relation": "imports_from", "confidence": "EXTRACTED", "source_file": "src\\components\\dashboard\\DashboardHomeClient.tsx", "source_location": "L7", "weight": 1.0}, {"source": "dashboardhomeclient", "target": "dashboardlibraryclient", "relation": "imports_from", "confidence": "EXTRACTED", "source_file": "src\\components\\dashboard\\DashboardHomeClient.tsx", "source_location": "L8", "weight": 1.0}, {"source": "dashboardhomeclient", "target": "dashboardmobilebottomnav", "relation": "imports_from", "confidence": "EXTRACTED", "source_file": "src\\components\\dashboard\\DashboardHomeClient.tsx", "source_location": "L9", "weight": 1.0}, {"source": "dashboardhomeclient", "target": "dashboardstatsrow", "relation": "imports_from", "confidence": "EXTRACTED", "source_file": "src\\components\\dashboard\\DashboardHomeClient.tsx", "source_location": "L10", "weight": 1.0}, {"source": "dashboardhomeclient", "target": "studysetdashboardlinks", "relation": "imports_from", "confidence": "EXTRACTED", "source_file": "src\\components\\dashboard\\DashboardHomeClient.tsx", "source_location": "L11", "weight": 1.0}, {"source": "dashboardhomeclient", "target": "usedashboardhome", "relation": "imports_from", "confidence": "EXTRACTED", "source_file": "src\\components\\dashboard\\DashboardHomeClient.tsx", "source_location": "L12", "weight": 1.0}, {"source": "dashboardhomeclient", "target": "dashboardhomeclient_scrolltohash", "relation": "contains", "confidence": "EXTRACTED", "source_file": "src\\components\\dashboard\\DashboardHomeClient.tsx", "source_location": "L38", "weight": 1.0}]}